{
	"format_version": "1.12.0",
	"minecraft:geometry": [
		{
			"description": {
				"identifier": "geometry.t-90",
				"texture_width": 1024,
				"texture_height": 1024,
				"visible_bounds_width": 10,
				"visible_bounds_height": 6,
				"visible_bounds_offset": [0, 2, 0]
			},
			"bones": [
				{
					"name": "T-90",
					"pivot": [0, 7, 0]
				},
				{
					"name": "body",
					"parent": "T-90",
					"pivot": [0, 7, -20],
					"cubes": [
						{"origin": [0, 7, -51], "size": [17, 3, 11], "pivot": [0, 7, -44], "rotation": [-25, 0, 0], "uv": [532, 269]},
						{"origin": [0, 6.8, -50], "size": [17, 1, 10], "pivot": [0, 7, -44], "rotation": [-25, 0, 0], "uv": [534, 175]},
						{"origin": [16, 9, -46], "size": [1, 7, 3], "pivot": [0, 7, -44], "rotation": [-25, 0, 0], "uv": [420, 602]},
						{"origin": [16, 9, -49], "size": [1, 6, 3], "pivot": [0, 7, -44], "rotation": [-25, 0, 0], "uv": [608, 543]},
						{"origin": [0, 12.48112, 42.91741], "size": [17, 6, 11.25], "pivot": [0, 12.48112, 51.66741], "rotation": [57.5, 0, 0], "uv": [524, 98]},
						{"origin": [-1.5, 12.48112, 42.91741], "size": [3, 5, 3.25], "pivot": [-1.5, 13.48112, 51.66741], "rotation": [57.5, 0, 0], "uv": [32, 598]},
						{"origin": [16, 14.48112, 47.66741], "size": [1, 6, 5.5], "pivot": [0, 12.48112, 51.66741], "rotation": [57.5, 0, 0], "uv": [96, 608]},
						{"origin": [0, 12.5937, -49.39823], "size": [17, 2, 26], "pivot": [0, 8.5937, -42.39823], "rotation": [20, 0, 0], "uv": [224, 512]},
						{"origin": [0, 14.5937, -39.39823], "size": [17, 1, 1], "pivot": [0, 8.5937, -42.39823], "rotation": [20, 0, 0], "uv": [364, 201]},
						{"origin": [14, 18.45615, -17.27482], "size": [3, 2, 28.25], "uv": [522, 28]},
						{"origin": [0, 18.45615, 10.72518], "size": [17, 2, 40.25], "uv": [0, 487]},
						{"origin": [0, 18.45615, -26.27482], "size": [17, 2, 9.25], "uv": [540, 547]},
						{"origin": [0, 20.45615, 25.72518], "size": [25, 2, 10.25], "uv": [492, 523]},
						{"origin": [24.25, 20.70615, 28.72518], "size": [2, 1, 4.25], "uv": [44, 582]},
						{"origin": [0, 19.95615, 37.72518], "size": [16, 2, 10.25], "uv": [224, 540]},
						{"origin": [2, 16.95615, 51.72518], "size": [13, 6, 6], "pivot": [8, 15.95615, 54.72518], "rotation": [-37.5, 0, 0], "uv": [310, 509]},
						{"origin": [-25, 11.95615, 53.72518], "size": [50, 3, 3], "pivot": [19, 10.95615, 56.72518], "rotation": [-37.5, 0, 0], "uv": [218, 189]},
						{"origin": [15.5, 11.95615, 49.97518], "size": [1, 4, 7], "pivot": [20.5, 10.95615, 55.97518], "rotation": [-37.5, 0, 0], "uv": [168, 426]},
						{"origin": [-16.5, 11.95615, 49.97518], "size": [1, 4, 7], "pivot": [-20.5, 10.95615, 55.97518], "rotation": [-37.5, 0, 0], "uv": [168, 437]},
						{"origin": [7, 19.95615, 49.72518], "size": [9, 2, 2.25], "uv": [348, 455]},
						{"origin": [17, 19.20615, -30.27482], "size": [9, 2, 84.25], "uv": [218, 103]},
						{"origin": [26, 12.20615, -30.27482], "size": [1, 8, 54.25], "uv": [348, 461]},
						{"origin": [26, 16.20615, 23.72518], "size": [1, 4, 30.25], "uv": [522, 118]},
						{"origin": [26, 12.20615, -48.27482], "size": [1, 4, 18.25], "uv": [548, 369]},
						{"origin": [26, 13.0735, 23.84773], "size": [1, 6, 29.25], "pivot": [26.5, 14.0735, 40.47273], "rotation": [3, 0, 0], "uv": [310, 523]},
						{"origin": [19, 20.95615, 8.72518], "size": [5, 1, 16.25], "uv": [548, 413]},
						{"origin": [19, 20.95615, 38.72518], "size": [5, 1, 12.25], "uv": [366, 558]},
						{"origin": [19, 20.95615, -12.27482], "size": [5, 1, 16.25], "uv": [548, 430]},
						{"origin": [19, 20.95615, -33.27482], "size": [5, 1, 16.25], "uv": [200, 552]},
						{"origin": [17, 18.25003, 50.83603], "size": [10, 2, 4], "pivot": [22.5, 15.25003, 52.33603], "rotation": [-35, 0, 0], "uv": [568, 516]},
						{"origin": [17, 13.20615, -30.27482], "size": [1, 6, 81.25], "uv": [184, 383]},
						{"origin": [17, 18.19841, -48.45919], "size": [9, 2, 18.25], "pivot": [21.5, 15.19841, -53.33419], "rotation": [2.5, 0, 0], "uv": [524, 58]},
						{"origin": [26, 13.19841, -48.45919], "size": [1, 6, 18.25], "pivot": [21.5, 15.19841, -53.33419], "rotation": [2.5, 0, 0], "uv": [548, 321]},
						{"origin": [17, 12.19841, -48.45919], "size": [1, 6, 18.25], "pivot": [21.5, 15.19841, -53.33419], "rotation": [2.5, 0, 0], "uv": [548, 297]},
						{"origin": [17, 13.51367, -50.94146], "size": [9, 2, 6.25], "pivot": [21.5, 10.51367, -55.81646], "rotation": [30, 0, 0], "uv": [556, 567]},
						{"origin": [17, 6.98157, -51.03493], "size": [1, 7, 5.25], "pivot": [21.5, 10.98157, -55.90993], "rotation": [30, 0, 0], "uv": [404, 178]},
						{"origin": [0, 5.12827, -40.45929], "size": [17, 6, 87.25], "uv": [0, 204]},
						{"origin": [-17, 7, -51], "size": [17, 3, 11], "pivot": [0, 7, -44], "rotation": [-25, 0, 0], "uv": [532, 281]},
						{"origin": [-17, 5.12827, -40.45929], "size": [17, 6, 87.25], "uv": [208, 204]},
						{"origin": [-17, 6.8, -50], "size": [17, 1, 10], "pivot": [0, 7, -44], "rotation": [-25, 0, 0], "uv": [534, 186]},
						{"origin": [16, 6.57738, -43.09369], "size": [1, 12, 91], "uv": [218, 0]},
						{"origin": [-17, 6.57738, -43.09369], "size": [1, 12, 91], "uv": [0, 297]},
						{"origin": [15, 8.57738, -44.09369], "size": [2, 11, 2], "uv": [340, 470]},
						{"origin": [-17, 9, -46], "size": [1, 7, 3], "pivot": [0, 7, -44], "rotation": [-25, 0, 0], "uv": [172, 606]},
						{"origin": [-17, 9, -49], "size": [1, 6, 3], "pivot": [0, 7, -44], "rotation": [-25, 0, 0], "uv": [16, 609]},
						{"origin": [-17, 12.48112, 42.91741], "size": [17, 6, 11.25], "pivot": [0, 12.48112, 51.66741], "rotation": [57.5, 0, 0], "uv": [0, 529]},
						{"origin": [-17, 14.48112, 47.66741], "size": [1, 6, 5.5], "pivot": [0, 12.48112, 51.66741], "rotation": [57.5, 0, 0], "uv": [608, 326]},
						{"origin": [-17, 12.5937, -49.39823], "size": [17, 2, 26], "pivot": [0, 8.5937, -42.39823], "rotation": [20, 0, 0], "uv": [522, 0]},
						{"origin": [-17, 14.5937, -39.39823], "size": [17, 1, 1], "pivot": [0, 8.5937, -42.39823], "rotation": [20, 0, 0], "uv": [310, 521]},
						{"origin": [-15, 14.5937, -49.39823], "size": [6, 1, 3], "pivot": [0, 8.5937, -42.39823], "rotation": [20, 0, 0], "uv": [400, 558]},
						{"origin": [-5, 14.5937, -49.39823], "size": [9, 1, 5], "pivot": [10, 8.5937, -42.39823], "rotation": [20, 0, 0], "uv": [274, 569]},
						{"origin": [9, 14.5937, -49.39823], "size": [6, 1, 3], "pivot": [24, 8.5937, -42.39823], "rotation": [20, 0, 0], "uv": [330, 580]},
						{"origin": [-17, 18.45615, 10.72518], "size": [17, 2, 40.25], "uv": [164, 470]},
						{"origin": [-17, 12.01816, 47.9918], "size": [34, 5, 6.25], "pivot": [8.5, 16.01816, 52.6168], "rotation": [-57.5, 0, 0], "uv": [522, 164]},
						{"origin": [-17, 18.45615, -26.27482], "size": [17, 2, 9.25], "uv": [0, 546]},
						{"origin": [-17, 18.45615, -17.27482], "size": [3, 2, 28.25], "uv": [430, 523]},
						{"origin": [-16, 20.45615, 25.72518], "size": [16, 2, 10.25], "uv": [56, 542]},
						{"origin": [-16, 19.95615, 37.72518], "size": [16, 2, 10.25], "uv": [540, 535]},
						{"origin": [-15, 16.95615, 51.72518], "size": [13, 6, 6], "pivot": [-8, 15.95615, 54.72518], "rotation": [-37.5, 0, 0], "uv": [328, 558]},
						{"origin": [-3, 19.95615, 49.72518], "size": [9, 2, 2.25], "uv": [288, 552]},
						{"origin": [-26, 19.20615, -30.27482], "size": [9, 2, 84.25], "uv": [184, 297]},
						{"origin": [-27, 12.20615, -30.27482], "size": [1, 8, 54.25], "uv": [458, 461]},
						{"origin": [-27, 15.20615, 23.72518], "size": [1, 5, 30.25], "uv": [278, 470]},
						{"origin": [-27, 12.20615, -48.27482], "size": [1, 4, 18.25], "uv": [548, 391]},
						{"origin": [-28, 12.70615, -21.27482], "size": [1, 8, 10.25], "uv": [348, 419]},
						{"origin": [-28, 12.20615, -32.27482], "size": [1, 8, 10.25], "uv": [348, 401]},
						{"origin": [-28, 11.70615, -43.27482], "size": [1, 8, 10.25], "uv": [348, 383]},
						{"origin": [27, 11.70615, -43.27482], "size": [1, 8, 10.25], "uv": [510, 565]},
						{"origin": [27, 12.20615, -32.27482], "size": [1, 8, 10.25], "uv": [140, 564]},
						{"origin": [27, 12.70615, -21.27482], "size": [1, 8, 10.25], "uv": [348, 437]},
						{"origin": [-27, 13.0735, 23.84773], "size": [1, 6, 29.25], "pivot": [-26.5, 14.0735, 40.47273], "rotation": [3, 0, 0], "uv": [370, 523]},
						{"origin": [-27, 14.68382, 51.79551], "size": [1, 3.75, 4.25], "pivot": [-26.5, 15.55882, 53.92051], "rotation": [40.5, 0, 0], "uv": [428, 591]},
						{"origin": [26, 14.68382, 51.79551], "size": [1, 3.75, 4.25], "pivot": [26.5, 15.55882, 53.92051], "rotation": [40.5, 0, 0], "uv": [138, 614]},
						{"origin": [-26, 18.25003, 50.83603], "size": [10, 2, 4], "pivot": [-20.5, 15.25003, 52.33603], "rotation": [-35, 0, 0], "uv": [192, 569]},
						{"origin": [-18, 13.20615, -30.27482], "size": [1, 6, 81.25], "uv": [0, 400]},
						{"origin": [-26, 18.19841, -48.45919], "size": [9, 2, 18.25], "pivot": [-21.5, 15.19841, -53.33419], "rotation": [2.5, 0, 0], "uv": [524, 78]},
						{"origin": [-27, 12.19841, -48.45919], "size": [1, 7, 18.25], "pivot": [-21.5, 15.19841, -53.33419], "rotation": [2.5, 0, 0], "uv": [162, 543]},
						{"origin": [-18, 12.19841, -48.45919], "size": [1, 6, 18.25], "pivot": [-21.5, 15.19841, -53.33419], "rotation": [2.5, 0, 0], "uv": [548, 345]},
						{"origin": [-26, 13.51367, -50.94146], "size": [9, 2, 6.25], "pivot": [-21.5, 10.51367, -55.81646], "rotation": [30, 0, 0], "uv": [162, 568]},
						{"origin": [-27, 12.51367, -50.94146], "size": [1, 2, 6.25], "pivot": [-21.5, 10.51367, -55.81646], "rotation": [30, 0, 0], "uv": [594, 452]},
						{"origin": [-27, 13.10955, -48.69291], "size": [1, 4, 3.25], "pivot": [-26.5, 15.10955, -48.56791], "rotation": [52.5, 0, 0], "uv": [184, 576]},
						{"origin": [-27, 13.10955, -50.69291], "size": [1, 5, 2.25], "pivot": [-26.5, 15.10955, -48.56791], "rotation": [52.5, 0, 0], "uv": [492, 602]},
						{"origin": [26, 13.10955, -50.69291], "size": [1, 5, 2.25], "pivot": [26.5, 15.10955, -48.56791], "rotation": [52.5, 0, 0], "uv": [420, 612]},
						{"origin": [26, 13.10955, -48.69291], "size": [1, 4, 3.25], "pivot": [26.5, 15.10955, -48.56791], "rotation": [52.5, 0, 0], "uv": [438, 583]},
						{"origin": [26, 12.51367, -50.94146], "size": [1, 2, 6.25], "pivot": [21.5, 10.51367, -55.81646], "rotation": [30, 0, 0], "uv": [600, 574]},
						{"origin": [-18, 6.98157, -51.03493], "size": [1, 7, 5.25], "pivot": [-21.5, 10.98157, -55.90993], "rotation": [30, 0, 0], "uv": [404, 190]},
						{"origin": [-17, 8.57738, -44.09369], "size": [2, 11, 2], "uv": [340, 483]}
					]
				},
				{
					"name": "turret",
					"parent": "T-90",
					"pivot": [0, 25, 0],
					"cubes": [
						{"origin": [-23.13397, 22, -6.37564], "size": [17, 7, 2], "pivot": [-20.13397, 25, -5.37564], "rotation": [0, 60, 0], "uv": [536, 558]},
						{"origin": [-23.13397, 20, -5.37564], "size": [17, 2, 2], "pivot": [-20.13397, 25, -5.37564], "rotation": [0, 60, 0], "uv": [0, 563]},
						{"origin": [-21.13397, 26, -5.37564], "size": [12, 4, 1], "pivot": [-20.13397, 25, -5.37564], "rotation": [65, 60, 0], "uv": [350, 571]},
						{"origin": [-21.05789, 26.02651, -5.33171], "size": [12, 8, 1], "pivot": [-20.05789, 29.02651, -5.33171], "rotation": [112.5, 60, 0], "uv": [568, 498]},
						{"origin": [-13.05789, 28.02651, -4.33171], "size": [4, 6, 2], "pivot": [-20.05789, 29.02651, -5.33171], "rotation": [112.5, 60, 0], "uv": [608, 337]},
						{"origin": [-15.23931, 30.92317, -12.78731], "size": [4, 3, 2], "pivot": [-13.23931, 30.92317, -11.78731], "rotation": [85, 60, 0], "uv": [608, 566]},
						{"origin": [9.05789, 26.02651, -5.33171], "size": [12, 8, 1], "pivot": [20.05789, 29.02651, -5.33171], "rotation": [112.5, -60, 0], "uv": [568, 507]},
						{"origin": [9.13397, 26, -5.37564], "size": [12, 4, 1], "pivot": [20.13397, 25, -5.37564], "rotation": [65, -60, 0], "uv": [376, 571]},
						{"origin": [9.05789, 28.02651, -4.33171], "size": [4, 6, 2], "pivot": [20.05789, 29.02651, -5.33171], "rotation": [112.5, -60, 0], "uv": [608, 345]},
						{"origin": [11.23931, 30.92317, -12.78731], "size": [4, 3, 2], "pivot": [13.23931, 30.92317, -11.78731], "rotation": [85, -60, 0], "uv": [108, 609]},
						{"origin": [-21.53991, 28.26219, -13.63073], "size": [17, 1, 12], "pivot": [-13.03991, 28.76219, -7.63073], "rotation": [2.5, 60, 0], "uv": [56, 529]},
						{"origin": [-31.77203, 22, 8.53611], "size": [29, 7, 2], "pivot": [-16.77203, 25, 9.53611], "rotation": [0, 110, 0], "uv": [218, 195]},
						{"origin": [-31.77203, 20, 9.53611], "size": [29, 2, 2], "pivot": [-16.77203, 25, 9.53611], "rotation": [0, 110, 0], "uv": [278, 505]},
						{"origin": [2.77203, 20, 9.53611], "size": [29, 2, 2], "pivot": [16.77203, 25, 9.53611], "rotation": [0, -110, 0], "uv": [532, 293]},
						{"origin": [6.13397, 20, -5.37564], "size": [17, 2, 2], "pivot": [20.13397, 25, -5.37564], "rotation": [0, -60, 0], "uv": [38, 563]},
						{"origin": [12.47244, 30, 18.74899], "size": [5, 2, 4], "pivot": [13.47244, 31, 20.74899], "rotation": [0, -142.5, 0], "uv": [446, 575]},
						{"origin": [-17.47244, 30, 18.74899], "size": [5, 2, 4], "pivot": [-13.47244, 31, 20.74899], "rotation": [0, 142.5, 0], "uv": [512, 583]},
						{"origin": [-2, 29, -11], "size": [5, 2, 4], "uv": [144, 557]},
						{"origin": [-8.27203, 27, 4.53611], "size": [1, 2, 4], "pivot": [-16.77203, 25, 9.53611], "rotation": [0, 110, 0], "uv": [22, 576]},
						{"origin": [-8.52203, 25, 4.53611], "size": [1, 2, 4], "pivot": [-16.77203, 25, 9.53611], "rotation": [0, 110, 0], "uv": [212, 614]},
						{"origin": [-8.77203, 23, 4.53611], "size": [1, 2, 4], "pivot": [-16.77203, 25, 9.53611], "rotation": [0, 110, 0], "uv": [222, 614]},
						{"origin": [-8.77203, 23.5, 7.03611], "size": [3, 1, 1], "pivot": [-16.77203, 25, 9.53611], "rotation": [0, 110, 0], "uv": [348, 459]},
						{"origin": [-7.52203, 25.5, 7.03611], "size": [2, 1, 1], "pivot": [-16.77203, 25, 9.53611], "rotation": [0, 110, 0], "uv": [410, 202]},
						{"origin": [-7.27203, 27.5, 7.03611], "size": [2, 1, 1], "pivot": [-16.77203, 25, 9.53611], "rotation": [0, 110, 0], "uv": [286, 509]},
						{"origin": [-7.27203, 27.5, 5.03611], "size": [2, 1, 1], "pivot": [-16.77203, 25, 9.53611], "rotation": [0, 110, 0], "uv": [292, 509]},
						{"origin": [-7.52203, 25.5, 5.03611], "size": [2, 1, 1], "pivot": [-16.77203, 25, 9.53611], "rotation": [0, 110, 0], "uv": [364, 459]},
						{"origin": [-8.77203, 23.5, 5.03611], "size": [3, 1, 1], "pivot": [-16.77203, 25, 9.53611], "rotation": [0, 110, 0], "uv": [356, 459]},
						{"origin": [5.27203, 27.5, 5.03611], "size": [2, 1, 1], "pivot": [16.77203, 25, 9.53611], "rotation": [0, -110, 0], "uv": [524, 115]},
						{"origin": [5.27203, 27.5, 7.03611], "size": [2, 1, 1], "pivot": [16.77203, 25, 9.53611], "rotation": [0, -110, 0], "uv": [522, 175]},
						{"origin": [7.27203, 27, 4.53611], "size": [1, 2, 4], "pivot": [16.77203, 25, 9.53611], "rotation": [0, -110, 0], "uv": [330, 614]},
						{"origin": [7.52203, 25, 4.53611], "size": [1, 2, 4], "pivot": [16.77203, 25, 9.53611], "rotation": [0, -110, 0], "uv": [320, 614]},
						{"origin": [7.77203, 23, 4.53611], "size": [1, 2, 4], "pivot": [16.77203, 25, 9.53611], "rotation": [0, -110, 0], "uv": [310, 614]},
						{"origin": [5.77203, 23.5, 5.03611], "size": [3, 1, 1], "pivot": [16.77203, 25, 9.53611], "rotation": [0, -110, 0], "uv": [278, 509]},
						{"origin": [5.77203, 23.5, 7.03611], "size": [3, 1, 1], "pivot": [16.77203, 25, 9.53611], "rotation": [0, -110, 0], "uv": [340, 507]},
						{"origin": [5.52203, 25.5, 5.03611], "size": [2, 1, 1], "pivot": [16.77203, 25, 9.53611], "rotation": [0, -110, 0], "uv": [304, 509]},
						{"origin": [5.52203, 25.5, 7.03611], "size": [2, 1, 1], "pivot": [16.77203, 25, 9.53611], "rotation": [0, -110, 0], "uv": [298, 509]},
						{"origin": [-12.77203, 22, 6.53611], "size": [3, 7, 2], "pivot": [-16.77203, 25, 9.53611], "rotation": [0, 110, 0], "uv": [378, 606]},
						{"origin": [-29.77203, 25, 4.53611], "size": [16, 4, 4], "pivot": [-16.77203, 25, 9.53611], "rotation": [0, 110, 0], "uv": [280, 195]},
						{"origin": [-28.8592, 23.68866, 4.20387], "size": [16, 3, 4], "pivot": [-15.8592, 22.68866, 9.20387], "rotation": [-162.5, 70, 180], "uv": [438, 562]},
						{"origin": [9.8592, 23.68866, 4.20387], "size": [19, 3, 4], "pivot": [15.8592, 22.68866, 9.20387], "rotation": [-162.5, -70, -180], "uv": [98, 557]},
						{"origin": [10.77203, 25, 4.53611], "size": [19, 4, 4], "pivot": [16.77203, 25, 9.53611], "rotation": [0, -110, 0], "uv": [114, 504]},
						{"origin": [4.53991, 28.26219, -13.63073], "size": [17, 1, 12], "pivot": [13.03991, 28.76219, -7.63073], "rotation": [2.5, -60, 0], "uv": [532, 247]},
						{"origin": [2.77203, 28.75, 8.53611], "size": [29, 1, 11], "pivot": [16.77203, 24.75, 9.53611], "rotation": [0, -110, 0], "uv": [522, 152]},
						{"origin": [-31.77203, 28.75, 8.53611], "size": [29, 1, 11], "pivot": [-16.77203, 24.75, 9.53611], "rotation": [0, 110, 0], "uv": [324, 189]},
						{"origin": [2.77203, 22, 8.53611], "size": [29, 7, 2], "pivot": [16.77203, 25, 9.53611], "rotation": [0, -110, 0], "uv": [532, 238]},
						{"origin": [6.13397, 22, -6.37564], "size": [17, 7, 2], "pivot": [20.13397, 25, -5.37564], "rotation": [0, -60, 0], "uv": [400, 562]},
						{"origin": [4, 24.75, -19.75], "size": [5, 3, 4], "pivot": [6.5, 26.25, -17.75], "rotation": [17.5, 0, 0], "uv": [164, 462]},
						{"origin": [-14, 22, -18], "size": [28, 7, 2], "uv": [532, 260]},
						{"origin": [-14, 20, -17], "size": [28, 2, 2], "uv": [534, 231]},
						{"origin": [-8, 25, -20], "size": [3, 6, 2], "pivot": [-6.5, 27.5, -19], "rotation": [-45, 0, 0], "uv": [608, 535]},
						{"origin": [-15, 25, -21], "size": [5, 5, 4], "uv": [164, 453]},
						{"origin": [10, 25, -21], "size": [5, 5, 4], "uv": [122, 573]},
						{"origin": [3, 28.08906, -17.96023], "size": [11, 1, 12], "pivot": [0, 28.58906, -16.96023], "rotation": [5, 0, 0], "uv": [548, 447]},
						{"origin": [-3, 28.08906, -12.96023], "size": [6, 1, 7], "pivot": [0, 28.58906, -16.96023], "rotation": [5, 0, 0], "uv": [302, 569]},
						{"origin": [-14, 28.08906, -17.96023], "size": [11, 1, 12], "pivot": [0, 28.58906, -16.96023], "rotation": [5, 0, 0], "uv": [242, 552]},
						{"origin": [-12.58142, 22, 21.97352], "size": [25, 8, 2], "uv": [108, 543]},
						{"origin": [-12.58142, 20, 20.97352], "size": [25, 2, 2], "uv": [108, 553]},
						{"origin": [-10.58142, 23.5, 23.97352], "size": [21, 7, 2], "uv": [430, 553]},
						{"origin": [-10.58142, 23.5, 27.97352], "size": [21, 3, 3], "pivot": [-0.08142, 24.5, 28.97352], "rotation": [27.5, 0, 0], "uv": [0, 557]},
						{"origin": [-10.58142, 22.5, 24.47352], "size": [21, 1, 1], "pivot": [-0.08142, 22.5, 25.47352], "rotation": [27.5, 0, 0], "uv": [320, 201]},
						{"origin": [-10.58142, 23.83496, 24.91502], "size": [21, 7, 2], "pivot": [1.41858, 25.83496, 23.91502], "rotation": [-12.5, 0, 0], "uv": [52, 554]},
						{"origin": [-12.58142, 29, -6.02648], "size": [25, 1, 30], "uv": [114, 512]},
						{"origin": [5.41858, 30, 14.97352], "size": [2, 2, 2], "uv": [206, 583]},
						{"origin": [-3.83142, 30, 18.97352], "size": [2, 9, 2], "uv": [340, 496]},
						{"origin": [5.41858, 32, 14.97352], "size": [1, 10, 1], "uv": [306, 540]},
						{"origin": [-3.33142, 39, 19.47352], "size": [1, 26, 1], "uv": [164, 426]},
						{"origin": [-13.58142, 29, 1.97352], "size": [11, 2, 11], "uv": [492, 552]},
						{"origin": [-13.08142, 31, 2.47352], "size": [10, 1, 10], "uv": [288, 558]},
						{"origin": [-12.08142, 31.5, 3.47352], "size": [8, 1, 8], "uv": [76, 564]},
						{"origin": [-0.58142, 29.75, 13.97352], "size": [4, 1, 4], "uv": [168, 448]},
						{"origin": [2.91858, 29.5, 14.47352], "size": [1, 1, 3], "uv": [416, 579]},
						{"origin": [3.41858, 29.25, 6.97352], "size": [9, 2, 4], "uv": [438, 569]},
						{"origin": [5.91858, 30.5, 6.72352], "size": [4, 1, 1], "uv": [400, 202]},
						{"origin": [5.39726, 30, 10.09484], "size": [4.9, 1, 3], "uv": [478, 561]},
						{"origin": [3.51478, 30, 11.74128], "size": [3, 1, 3], "pivot": [8.01478, 30.5, 12.74128], "rotation": [0, -45, 0], "uv": [418, 558]},
						{"origin": [8.27214, 30, 11.74128], "size": [3, 1, 3], "pivot": [12.77214, 30.5, 12.74128], "rotation": [0, -45, 0], "uv": [274, 565]},
						{"origin": [7.66858, 30, -2.27648], "size": [6, 1, 6], "uv": [200, 543]},
						{"origin": [14.66858, 29.5, -3.27648], "size": [2, 3, 2], "uv": [24, 609]},
						{"origin": [14.66858, 31.5, -4.27648], "size": [2, 2, 2], "uv": [424, 571]},
						{"origin": [8.66858, 30, -1.27648], "size": [4, 4, 4], "uv": [476, 553]},
						{"origin": [9.16858, 30, -1.77648], "size": [3, 4, 1], "uv": [124, 598]},
						{"origin": [8.66858, 34, -2.27648], "size": [4, 1, 5], "uv": [56, 567]},
						{"origin": [-5.18142, 29.75, -6.02648], "size": [2, 1, 4], "uv": [212, 609]},
						{"origin": [-7.28142, 29.75, -2.82648], "size": [2, 1, 4], "pivot": [-6.28142, 30.25, -0.82648], "rotation": [0, 70, 0], "uv": [610, 183]},
						{"origin": [-10.98142, 29.75, -11.42648], "size": [2, 1, 4], "pivot": [-9.98142, 30.25, -9.42648], "rotation": [0, -30, 0], "uv": [516, 609]},
						{"origin": [-13.08142, 29.75, -7.87648], "size": [2, 1, 4], "pivot": [-12.08142, 30.25, -5.87648], "rotation": [0, -30, 0], "uv": [610, 173]},
						{"origin": [-15.18142, 29.75, -4.27648], "size": [2, 1, 4], "pivot": [-14.18142, 30.25, -2.27648], "rotation": [0, -30, 0], "uv": [610, 178]},
						{"origin": [-2.88142, 29.75, -6.02648], "size": [2, 1, 4], "uv": [224, 609]},
						{"origin": [-0.58142, 29.75, -6.02648], "size": [2, 1, 4], "uv": [388, 609]},
						{"origin": [1.61858, 29.75, -6.02648], "size": [2, 1, 4], "uv": [428, 609]},
						{"origin": [3.81858, 29.75, -6.02648], "size": [2, 1, 4], "uv": [440, 609]},
						{"origin": [0.46858, 29.75, -1.77648], "size": [2, 1, 4], "uv": [492, 609]},
						{"origin": [1.61858, 29.75, 2.47352], "size": [2, 1, 4], "uv": [504, 609]},
						{"origin": [-2.38142, 29.75, 20.47352], "size": [2, 1, 4], "pivot": [-1.38142, 30.25, 22.47352], "rotation": [0, -90, 0], "uv": [610, 229]},
						{"origin": [5.11858, 29.75, 20.47352], "size": [2, 1, 4], "pivot": [6.11858, 30.25, 22.47352], "rotation": [0, -90, 0], "uv": [610, 276]},
						{"origin": [-6.38142, 29.75, 18.47352], "size": [2, 1, 4], "uv": [610, 234]},
						{"origin": [1.61858, 29.75, 19.47352], "size": [2, 1, 4], "pivot": [2.61858, 30.25, 21.47352], "rotation": [0, -12.5, 0], "uv": [610, 271]},
						{"origin": [-4.38142, 29.75, 14.47352], "size": [2, 1, 4], "pivot": [-3.38142, 30.25, 16.47352], "rotation": [0, 45, 0], "uv": [610, 266]},
						{"origin": [2.66858, 29.75, -1.77648], "size": [2, 1, 4], "uv": [464, 609]},
						{"origin": [4.86858, 29.75, -1.77648], "size": [2, 1, 4], "uv": [452, 609]}
					]
				},
				{
					"name": "barrel",
					"parent": "turret",
					"pivot": [0, 25, -17],
					"cubes": [
						{"origin": [-3, 22, -19], "size": [6, 8, 6], "uv": [568, 460]},
						{"origin": [-2, 25, -80], "size": [1, 2, 58], "uv": [404, 118]},
						{"origin": [1, 25, -80], "size": [1, 2, 58], "uv": [416, 178]},
						{"origin": [-1, 24, -80], "size": [2, 1, 58], "uv": [402, 0]},
						{"origin": [-1, 27, -80], "size": [2, 1, 58], "uv": [404, 59]},
						{"origin": [-2, 24, -22], "size": [1, 4, 9], "uv": [164, 413]},
						{"origin": [-1, 27, -22], "size": [2, 1, 9], "uv": [328, 570]},
						{"origin": [1, 24, -22], "size": [1, 4, 9], "uv": [164, 400]},
						{"origin": [1.25, 24, -58], "size": [1, 4, 11], "uv": [532, 567]},
						{"origin": [-2, 23.75, -58], "size": [4, 1, 11], "uv": [562, 523]},
						{"origin": [-2.25, 24, -58], "size": [1, 4, 11], "uv": [32, 567]},
						{"origin": [-2, 27.25, -58], "size": [4, 1, 11], "uv": [276, 540]},
						{"origin": [1.19751, 24, -20.72257], "size": [4, 4, 8], "pivot": [3.19751, 26, -13.72257], "rotation": [0, 25, 0], "uv": [568, 474]},
						{"origin": [-5.19751, 24, -20.72257], "size": [4, 4, 8], "pivot": [-3.19751, 26, -13.72257], "rotation": [0, -25, 0], "uv": [568, 486]},
						{"origin": [-2, 27.41421, -20.75736], "size": [4, 4, 3], "pivot": [0, 29.41421, -16.75736], "rotation": [45, 0, 0], "uv": [498, 591]},
						{"origin": [-2, 24.41421, -20.75736], "size": [4, 3, 3], "pivot": [0, 25.41421, -16.75736], "rotation": [45, 0, 0], "uv": [584, 52]},
						{"origin": [0, 27.25, -80], "size": [0, 1, 58], "uv": [416, 238]},
						{"origin": [-1, 24, -22], "size": [2, 1, 9], "uv": [220, 569]}
					]
				},
				{
					"name": "wheelL",
					"parent": "T-90",
					"pivot": [0, 6, -3.25]
				},
				{
					"name": "wheel1",
					"parent": "wheelL",
					"pivot": [22.25, 9.58952, -46.375],
					"cubes": [
						{"origin": [21, 5.425, -48.1], "size": [2, 4.6, 3.45], "uv": [314, 596]},
						{"origin": [21, 7.05134, -50.87634], "size": [2, 4.6, 3.45], "pivot": [22, 7.05134, -49.72634], "rotation": [-45, 0, 0], "uv": [236, 609]},
						{"origin": [21, 10.16452, -51.68952], "size": [2, 4.6, 3.45], "pivot": [22, 10.16452, -50.53952], "rotation": [-90, 0, 0], "uv": [610, 281]},
						{"origin": [21, 12.94086, -50.06318], "size": [2, 4.6, 3.45], "pivot": [22, 12.94086, -48.91318], "rotation": [-135, 0, 0], "uv": [610, 441]},
						{"origin": [21, 13.75404, -46.95], "size": [2, 4.6, 3.45], "pivot": [22, 13.75404, -45.8], "rotation": [180, 0, 0], "uv": [610, 492]},
						{"origin": [21, 12.12769, -44.17366], "size": [2, 4.6, 3.45], "pivot": [22, 12.12769, -43.02366], "rotation": [135, 0, 0], "uv": [610, 499]},
						{"origin": [21, 9.01452, -43.36048], "size": [2, 4.6, 3.45], "pivot": [22, 9.01452, -42.21048], "rotation": [90, 0, 0], "uv": [610, 506]},
						{"origin": [21, 6.23818, -44.98682], "size": [2, 4.6, 3.45], "pivot": [22, 6.23818, -43.83682], "rotation": [45, 0, 0], "uv": [610, 513]},
						{"origin": [21, 5.425, -48.1], "size": [4, 2.3, 3.45], "uv": [606, 140]},
						{"origin": [21, 6.23818, -44.98682], "size": [4, 2.3, 3.45], "pivot": [22, 6.23818, -43.83682], "rotation": [45, 0, 0], "uv": [604, 224]},
						{"origin": [21, 9.01452, -43.36048], "size": [4, 2.3, 3.45], "pivot": [22, 9.01452, -42.21048], "rotation": [90, 0, 0], "uv": [602, 168]},
						{"origin": [21, 12.12769, -44.17366], "size": [4, 2.3, 3.45], "pivot": [22, 12.12769, -43.02366], "rotation": [135, 0, 0], "uv": [596, 515]},
						{"origin": [21, 13.75404, -46.95], "size": [4, 2.3, 3.45], "pivot": [22, 13.75404, -45.8], "rotation": [180, 0, 0], "uv": [594, 240]},
						{"origin": [21, 7.05134, -50.87634], "size": [4, 2.3, 3.45], "pivot": [22, 7.05134, -49.72634], "rotation": [-45, 0, 0], "uv": [588, 191]},
						{"origin": [21, 10.16452, -51.68952], "size": [4, 2.3, 3.45], "pivot": [22, 10.16452, -50.53952], "rotation": [-90, 0, 0], "uv": [584, 146]},
						{"origin": [21, 12.94086, -50.06318], "size": [4, 2.3, 3.45], "pivot": [22, 12.94086, -48.91318], "rotation": [-135, 0, 0], "uv": [464, 569]}
					]
				},
				{
					"name": "wheel2",
					"parent": "wheelL",
					"pivot": [22.25, 9.58952, 47.925],
					"cubes": [
						{"origin": [21, 5.425, 46.2], "size": [2, 4.6, 3.45], "uv": [610, 605]},
						{"origin": [21, 7.05134, 48.97634], "size": [2, 4.6, 3.45], "pivot": [22, 7.05134, 51.27634], "rotation": [45, 0, 0], "uv": [612, 245]},
						{"origin": [21, 10.16452, 49.78952], "size": [2, 4.6, 3.45], "pivot": [22, 10.16452, 52.08952], "rotation": [90, 0, 0], "uv": [612, 408]},
						{"origin": [21, 12.94086, 48.16318], "size": [2, 4.6, 3.45], "pivot": [22, 12.94086, 50.46318], "rotation": [135, 0, 0], "uv": [612, 415]},
						{"origin": [21, 13.75404, 45.05], "size": [2, 4.6, 3.45], "pivot": [22, 13.75404, 47.35], "rotation": [-180, 0, 0], "uv": [612, 422]},
						{"origin": [21, 12.12769, 42.27366], "size": [2, 4.6, 3.45], "pivot": [22, 12.12769, 44.57366], "rotation": [-135, 0, 0], "uv": [612, 429]},
						{"origin": [21, 9.01452, 41.46048], "size": [2, 4.6, 3.45], "pivot": [22, 9.01452, 43.76048], "rotation": [-90, 0, 0], "uv": [528, 612]},
						{"origin": [21, 6.23818, 43.08682], "size": [2, 4.6, 3.45], "pivot": [22, 6.23818, 45.38682], "rotation": [-45, 0, 0], "uv": [612, 552]},
						{"origin": [21, 5.425, 46.2], "size": [4, 2.3, 3.45], "uv": [608, 22]},
						{"origin": [21, 6.23818, 43.08682], "size": [4, 2.3, 3.45], "pivot": [22, 6.23818, 45.38682], "rotation": [-45, 0, 0], "uv": [608, 240]},
						{"origin": [21, 9.01452, 41.46048], "size": [4, 2.3, 3.45], "pivot": [22, 9.01452, 43.76048], "rotation": [-90, 0, 0], "uv": [608, 353]},
						{"origin": [21, 12.12769, 42.27366], "size": [4, 2.3, 3.45], "pivot": [22, 12.12769, 44.57366], "rotation": [-135, 0, 0], "uv": [608, 358]},
						{"origin": [21, 13.75404, 45.05], "size": [4, 2.3, 3.45], "pivot": [22, 13.75404, 47.35], "rotation": [-180, 0, 0], "uv": [608, 363]},
						{"origin": [21, 7.05134, 48.97634], "size": [4, 2.3, 3.45], "pivot": [22, 7.05134, 51.27634], "rotation": [45, 0, 0], "uv": [608, 368]},
						{"origin": [21, 10.16452, 49.78952], "size": [4, 2.3, 3.45], "pivot": [22, 10.16452, 52.08952], "rotation": [90, 0, 0], "uv": [608, 373]},
						{"origin": [21, 12.94086, 48.16318], "size": [4, 2.3, 3.45], "pivot": [22, 12.94086, 50.46318], "rotation": [135, 0, 0], "uv": [608, 378]}
					]
				},
				{
					"name": "wheel3",
					"parent": "wheelL",
					"pivot": [20.25, 7.57702, 36.425],
					"cubes": [
						{"origin": [18.375, 1.33024, 33.8375], "size": [3, 6.9, 5.175], "uv": [166, 584]},
						{"origin": [18.375, 3.76976, 38.00202], "size": [3, 6.9, 5.175], "pivot": [19.875, 3.76976, 41.45202], "rotation": [45, 0, 0], "uv": [396, 587]},
						{"origin": [18.375, 8.43952, 39.22178], "size": [3, 6.9, 5.175], "pivot": [19.875, 8.43952, 42.67178], "rotation": [90, 0, 0], "uv": [534, 590]},
						{"origin": [18.375, 12.60404, 36.78226], "size": [3, 6.9, 5.175], "pivot": [19.875, 12.60404, 40.23226], "rotation": [135, 0, 0], "uv": [182, 591]},
						{"origin": [18.375, 13.8238, 32.1125], "size": [3, 6.9, 5.175], "pivot": [19.875, 13.8238, 35.5625], "rotation": [-180, 0, 0], "uv": [250, 591]},
						{"origin": [18.375, 11.38428, 27.94798], "size": [3, 6.9, 5.175], "pivot": [19.875, 11.38428, 31.39798], "rotation": [-135, 0, 0], "uv": [412, 591]},
						{"origin": [18.375, 6.71452, 26.72822], "size": [3, 6.9, 5.175], "pivot": [19.875, 6.71452, 30.17822], "rotation": [-90, 0, 0], "uv": [482, 591]},
						{"origin": [18.375, 2.55, 29.16774], "size": [3, 6.9, 5.175], "pivot": [19.875, 2.55, 32.61774], "rotation": [-45, 0, 0], "uv": [550, 591]},
						{"origin": [18.375, 1.33024, 33.8375], "size": [6, 3.45, 5.175], "uv": [402, 571]},
						{"origin": [18.375, 2.55, 29.16774], "size": [6, 3.45, 5.175], "pivot": [19.875, 2.55, 32.61774], "rotation": [-45, 0, 0], "uv": [56, 573]},
						{"origin": [18.375, 6.71452, 26.72822], "size": [6, 3.45, 5.175], "pivot": [19.875, 6.71452, 30.17822], "rotation": [-90, 0, 0], "uv": [78, 573]},
						{"origin": [18.375, 11.38428, 27.94798], "size": [6, 3.45, 5.175], "pivot": [19.875, 11.38428, 31.39798], "rotation": [-135, 0, 0], "uv": [100, 573]},
						{"origin": [18.375, 13.8238, 32.1125], "size": [6, 3.45, 5.175], "pivot": [19.875, 13.8238, 35.5625], "rotation": [-180, 0, 0], "uv": [242, 574]},
						{"origin": [18.375, 3.76976, 38.00202], "size": [6, 3.45, 5.175], "pivot": [19.875, 3.76976, 41.45202], "rotation": [45, 0, 0], "uv": [464, 574]},
						{"origin": [18.375, 8.43952, 39.22178], "size": [6, 3.45, 5.175], "pivot": [19.875, 8.43952, 42.67178], "rotation": [90, 0, 0], "uv": [486, 574]},
						{"origin": [18.375, 12.60404, 36.78226], "size": [6, 3.45, 5.175], "pivot": [19.875, 12.60404, 40.23226], "rotation": [135, 0, 0], "uv": [574, 558]}
					]
				},
				{
					"name": "wheel4",
					"parent": "wheelL",
					"pivot": [20.25, 7.57702, 8.825],
					"cubes": [
						{"origin": [18.375, 1.33024, 6.2375], "size": [3, 6.9, 5.175], "uv": [356, 592]},
						{"origin": [18.375, 3.76976, 10.40202], "size": [3, 6.9, 5.175], "pivot": [19.875, 3.76976, 13.85202], "rotation": [45, 0, 0], "uv": [592, 460]},
						{"origin": [18.375, 8.43952, 11.62178], "size": [3, 6.9, 5.175], "pivot": [19.875, 8.43952, 15.07178], "rotation": [90, 0, 0], "uv": [592, 471]},
						{"origin": [18.375, 12.60404, 9.18226], "size": [3, 6.9, 5.175], "pivot": [19.875, 12.60404, 12.63226], "rotation": [135, 0, 0], "uv": [592, 482]},
						{"origin": [18.375, 13.8238, 4.5125], "size": [3, 6.9, 5.175], "pivot": [19.875, 13.8238, 7.9625], "rotation": [-180, 0, 0], "uv": [592, 522]},
						{"origin": [18.375, 11.38428, 0.34798], "size": [3, 6.9, 5.175], "pivot": [19.875, 11.38428, 3.79798], "rotation": [-135, 0, 0], "uv": [592, 533]},
						{"origin": [18.375, 6.71452, -0.87178], "size": [3, 6.9, 5.175], "pivot": [19.875, 6.71452, 2.57822], "rotation": [-90, 0, 0], "uv": [592, 544]},
						{"origin": [18.375, 2.55, 1.56774], "size": [3, 6.9, 5.175], "pivot": [19.875, 2.55, 5.01774], "rotation": [-45, 0, 0], "uv": [266, 593]},
						{"origin": [18.375, 1.33024, 6.2375], "size": [6, 3.45, 5.175], "uv": [286, 577]},
						{"origin": [18.375, 2.55, 1.56774], "size": [6, 3.45, 5.175], "pivot": [19.875, 2.55, 5.01774], "rotation": [-45, 0, 0], "uv": [578, 58]},
						{"origin": [18.375, 6.71452, -0.87178], "size": [6, 3.45, 5.175], "pivot": [19.875, 6.71452, 2.57822], "rotation": [-90, 0, 0], "uv": [578, 66]},
						{"origin": [18.375, 11.38428, 0.34798], "size": [6, 3.45, 5.175], "pivot": [19.875, 11.38428, 3.79798], "rotation": [-135, 0, 0], "uv": [578, 74]},
						{"origin": [18.375, 13.8238, 4.5125], "size": [6, 3.45, 5.175], "pivot": [19.875, 13.8238, 7.9625], "rotation": [-180, 0, 0], "uv": [578, 82]},
						{"origin": [18.375, 3.76976, 10.40202], "size": [6, 3.45, 5.175], "pivot": [19.875, 3.76976, 13.85202], "rotation": [45, 0, 0], "uv": [578, 90]},
						{"origin": [18.375, 8.43952, 11.62178], "size": [6, 3.45, 5.175], "pivot": [19.875, 8.43952, 15.07178], "rotation": [90, 0, 0], "uv": [578, 575]},
						{"origin": [18.375, 12.60404, 9.18226], "size": [6, 3.45, 5.175], "pivot": [19.875, 12.60404, 12.63226], "rotation": [135, 0, 0], "uv": [214, 579]}
					]
				},
				{
					"name": "wheel5",
					"parent": "wheelL",
					"pivot": [20.25, 7.57702, 22.625],
					"cubes": [
						{"origin": [18.375, 1.33024, 20.0375], "size": [3, 6.9, 5.175], "uv": [566, 591]},
						{"origin": [18.375, 3.76976, 24.20202], "size": [3, 6.9, 5.175], "pivot": [19.875, 3.76976, 27.65202], "rotation": [45, 0, 0], "uv": [582, 591]},
						{"origin": [18.375, 8.43952, 25.42178], "size": [3, 6.9, 5.175], "pivot": [19.875, 8.43952, 28.87178], "rotation": [90, 0, 0], "uv": [0, 592]},
						{"origin": [18.375, 12.60404, 22.98226], "size": [3, 6.9, 5.175], "pivot": [19.875, 12.60404, 26.43226], "rotation": [135, 0, 0], "uv": [132, 592]},
						{"origin": [18.375, 13.8238, 18.3125], "size": [3, 6.9, 5.175], "pivot": [19.875, 13.8238, 21.7625], "rotation": [-180, 0, 0], "uv": [148, 592]},
						{"origin": [18.375, 11.38428, 14.14798], "size": [3, 6.9, 5.175], "pivot": [19.875, 11.38428, 17.59798], "rotation": [-135, 0, 0], "uv": [592, 255]},
						{"origin": [18.375, 6.71452, 12.92822], "size": [3, 6.9, 5.175], "pivot": [19.875, 6.71452, 16.37822], "rotation": [-90, 0, 0], "uv": [324, 592]},
						{"origin": [18.375, 2.55, 15.36774], "size": [3, 6.9, 5.175], "pivot": [19.875, 2.55, 18.81774], "rotation": [-45, 0, 0], "uv": [340, 592]},
						{"origin": [18.375, 1.33024, 20.0375], "size": [6, 3.45, 5.175], "uv": [192, 575]},
						{"origin": [18.375, 2.55, 15.36774], "size": [6, 3.45, 5.175], "pivot": [19.875, 2.55, 18.81774], "rotation": [-45, 0, 0], "uv": [264, 575]},
						{"origin": [18.375, 6.71452, 12.92822], "size": [6, 3.45, 5.175], "pivot": [19.875, 6.71452, 16.37822], "rotation": [-90, 0, 0], "uv": [424, 575]},
						{"origin": [18.375, 11.38428, 14.14798], "size": [6, 3.45, 5.175], "pivot": [19.875, 11.38428, 17.59798], "rotation": [-135, 0, 0], "uv": [556, 575]},
						{"origin": [18.375, 13.8238, 18.3125], "size": [6, 3.45, 5.175], "pivot": [19.875, 13.8238, 21.7625], "rotation": [-180, 0, 0], "uv": [0, 576]},
						{"origin": [18.375, 3.76976, 24.20202], "size": [6, 3.45, 5.175], "pivot": [19.875, 3.76976, 27.65202], "rotation": [45, 0, 0], "uv": [162, 576]},
						{"origin": [18.375, 8.43952, 25.42178], "size": [6, 3.45, 5.175], "pivot": [19.875, 8.43952, 28.87178], "rotation": [90, 0, 0], "uv": [350, 576]},
						{"origin": [18.375, 12.60404, 22.98226], "size": [6, 3.45, 5.175], "pivot": [19.875, 12.60404, 26.43226], "rotation": [135, 0, 0], "uv": [372, 576]}
					]
				},
				{
					"name": "wheel6",
					"parent": "wheelL",
					"pivot": [20.25, 7.57702, -6.125],
					"cubes": [
						{"origin": [18.375, 1.33024, -8.7125], "size": [3, 6.9, 5.175], "uv": [282, 593]},
						{"origin": [18.375, 3.76976, -4.54798], "size": [3, 6.9, 5.175], "pivot": [19.875, 3.76976, -1.09798], "rotation": [45, 0, 0], "uv": [594, 229]},
						{"origin": [18.375, 8.43952, -3.32822], "size": [3, 6.9, 5.175], "pivot": [19.875, 8.43952, 0.12178], "rotation": [90, 0, 0], "uv": [594, 441]},
						{"origin": [18.375, 12.60404, -5.76774], "size": [3, 6.9, 5.175], "pivot": [19.875, 12.60404, -2.31774], "rotation": [135, 0, 0], "uv": [594, 493]},
						{"origin": [18.375, 13.8238, -10.4375], "size": [3, 6.9, 5.175], "pivot": [19.875, 13.8238, -6.9875], "rotation": [-180, 0, 0], "uv": [594, 504]},
						{"origin": [18.375, 11.38428, -14.60202], "size": [3, 6.9, 5.175], "pivot": [19.875, 11.38428, -11.15202], "rotation": [-135, 0, 0], "uv": [164, 595]},
						{"origin": [18.375, 6.71452, -15.82178], "size": [3, 6.9, 5.175], "pivot": [19.875, 6.71452, -12.37178], "rotation": [-90, 0, 0], "uv": [198, 595]},
						{"origin": [18.375, 2.55, -13.38226], "size": [3, 6.9, 5.175], "pivot": [19.875, 2.55, -9.93226], "rotation": [-45, 0, 0], "uv": [372, 595]},
						{"origin": [18.375, 1.33024, -8.7125], "size": [6, 3.45, 5.175], "uv": [394, 579]},
						{"origin": [18.375, 2.55, -13.38226], "size": [6, 3.45, 5.175], "pivot": [19.875, 2.55, -9.93226], "rotation": [-45, 0, 0], "uv": [580, 98]},
						{"origin": [18.375, 6.71452, -15.82178], "size": [6, 3.45, 5.175], "pivot": [19.875, 6.71452, -12.37178], "rotation": [-90, 0, 0], "uv": [580, 106]},
						{"origin": [18.375, 11.38428, -14.60202], "size": [6, 3.45, 5.175], "pivot": [19.875, 11.38428, -11.15202], "rotation": [-135, 0, 0], "uv": [308, 580]},
						{"origin": [18.375, 13.8238, -10.4375], "size": [6, 3.45, 5.175], "pivot": [19.875, 13.8238, -6.9875], "rotation": [-180, 0, 0], "uv": [56, 581]},
						{"origin": [18.375, 3.76976, -4.54798], "size": [6, 3.45, 5.175], "pivot": [19.875, 3.76976, -1.09798], "rotation": [45, 0, 0], "uv": [78, 581]},
						{"origin": [18.375, 8.43952, -3.32822], "size": [6, 3.45, 5.175], "pivot": [19.875, 8.43952, 0.12178], "rotation": [90, 0, 0], "uv": [100, 581]},
						{"origin": [18.375, 12.60404, -5.76774], "size": [6, 3.45, 5.175], "pivot": [19.875, 12.60404, -2.31774], "rotation": [135, 0, 0], "uv": [22, 582]}
					]
				},
				{
					"name": "wheel7",
					"parent": "wheelL",
					"pivot": [20.25, 7.57702, -19.925],
					"cubes": [
						{"origin": [18.375, 1.33024, -22.5125], "size": [3, 6.9, 5.175], "uv": [298, 596]},
						{"origin": [18.375, 3.76976, -18.34798], "size": [3, 6.9, 5.175], "pivot": [19.875, 3.76976, -14.89798], "rotation": [45, 0, 0], "uv": [596, 555]},
						{"origin": [18.375, 8.43952, -17.12822], "size": [3, 6.9, 5.175], "pivot": [19.875, 8.43952, -13.67822], "rotation": [90, 0, 0], "uv": [44, 597]},
						{"origin": [18.375, 12.60404, -19.56774], "size": [3, 6.9, 5.175], "pivot": [19.875, 12.60404, -16.11774], "rotation": [135, 0, 0], "uv": [60, 597]},
						{"origin": [18.375, 13.8238, -24.2375], "size": [3, 6.9, 5.175], "pivot": [19.875, 13.8238, -20.7875], "rotation": [-180, 0, 0], "uv": [76, 597]},
						{"origin": [18.375, 11.38428, -28.40202], "size": [3, 6.9, 5.175], "pivot": [19.875, 11.38428, -24.95202], "rotation": [-135, 0, 0], "uv": [92, 597]},
						{"origin": [18.375, 6.71452, -29.62178], "size": [3, 6.9, 5.175], "pivot": [19.875, 6.71452, -26.17178], "rotation": [-90, 0, 0], "uv": [16, 598]},
						{"origin": [18.375, 2.55, -27.18226], "size": [3, 6.9, 5.175], "pivot": [19.875, 2.55, -23.73226], "rotation": [-45, 0, 0], "uv": [108, 598]},
						{"origin": [18.375, 1.33024, -22.5125], "size": [6, 3.45, 5.175], "uv": [122, 582]},
						{"origin": [18.375, 2.55, -27.18226], "size": [6, 3.45, 5.175], "pivot": [19.875, 2.55, -23.73226], "rotation": [-45, 0, 0], "uv": [582, 197]},
						{"origin": [18.375, 6.71452, -29.62178], "size": [6, 3.45, 5.175], "pivot": [19.875, 6.71452, -26.17178], "rotation": [-90, 0, 0], "uv": [582, 205]},
						{"origin": [18.375, 11.38428, -28.40202], "size": [6, 3.45, 5.175], "pivot": [19.875, 11.38428, -24.95202], "rotation": [-135, 0, 0], "uv": [582, 213]},
						{"origin": [18.375, 13.8238, -24.2375], "size": [6, 3.45, 5.175], "pivot": [19.875, 13.8238, -20.7875], "rotation": [-180, 0, 0], "uv": [582, 221]},
						{"origin": [18.375, 3.76976, -18.34798], "size": [6, 3.45, 5.175], "pivot": [19.875, 3.76976, -14.89798], "rotation": [45, 0, 0], "uv": [236, 582]},
						{"origin": [18.375, 8.43952, -17.12822], "size": [6, 3.45, 5.175], "pivot": [19.875, 8.43952, -13.67822], "rotation": [90, 0, 0], "uv": [446, 582]},
						{"origin": [18.375, 12.60404, -19.56774], "size": [6, 3.45, 5.175], "pivot": [19.875, 12.60404, -16.11774], "rotation": [135, 0, 0], "uv": [468, 582]}
					]
				},
				{
					"name": "wheel8",
					"parent": "wheelL",
					"pivot": [20.25, 7.57702, -33.725],
					"cubes": [
						{"origin": [18.375, 1.33024, -36.3125], "size": [3, 6.9, 5.175], "uv": [214, 598]},
						{"origin": [18.375, 3.76976, -32.14798], "size": [3, 6.9, 5.175], "pivot": [19.875, 3.76976, -28.69798], "rotation": [45, 0, 0], "uv": [230, 598]},
						{"origin": [18.375, 8.43952, -30.92822], "size": [3, 6.9, 5.175], "pivot": [19.875, 8.43952, -27.47822], "rotation": [90, 0, 0], "uv": [388, 598]},
						{"origin": [18.375, 12.60404, -33.36774], "size": [3, 6.9, 5.175], "pivot": [19.875, 12.60404, -29.91774], "rotation": [135, 0, 0], "uv": [428, 598]},
						{"origin": [18.375, 13.8238, -38.0375], "size": [3, 6.9, 5.175], "pivot": [19.875, 13.8238, -34.5875], "rotation": [-180, 0, 0], "uv": [444, 598]},
						{"origin": [18.375, 11.38428, -42.20202], "size": [3, 6.9, 5.175], "pivot": [19.875, 11.38428, -38.75202], "rotation": [-135, 0, 0], "uv": [460, 598]},
						{"origin": [18.375, 6.71452, -43.42178], "size": [3, 6.9, 5.175], "pivot": [19.875, 6.71452, -39.97178], "rotation": [-90, 0, 0], "uv": [498, 598]},
						{"origin": [18.375, 2.55, -40.98226], "size": [3, 6.9, 5.175], "pivot": [19.875, 2.55, -37.53226], "rotation": [-45, 0, 0], "uv": [514, 598]},
						{"origin": [18.375, 1.33024, -36.3125], "size": [6, 3.45, 5.175], "uv": [532, 582]},
						{"origin": [18.375, 2.55, -40.98226], "size": [6, 3.45, 5.175], "pivot": [19.875, 2.55, -37.53226], "rotation": [-45, 0, 0], "uv": [184, 583]},
						{"origin": [18.375, 6.71452, -43.42178], "size": [6, 3.45, 5.175], "pivot": [19.875, 6.71452, -39.97178], "rotation": [-90, 0, 0], "uv": [258, 583]},
						{"origin": [18.375, 11.38428, -42.20202], "size": [6, 3.45, 5.175], "pivot": [19.875, 11.38428, -38.75202], "rotation": [-135, 0, 0], "uv": [416, 583]},
						{"origin": [18.375, 13.8238, -38.0375], "size": [6, 3.45, 5.175], "pivot": [19.875, 13.8238, -34.5875], "rotation": [-180, 0, 0], "uv": [490, 583]},
						{"origin": [18.375, 3.76976, -32.14798], "size": [6, 3.45, 5.175], "pivot": [19.875, 3.76976, -28.69798], "rotation": [45, 0, 0], "uv": [554, 583]},
						{"origin": [18.375, 8.43952, -30.92822], "size": [6, 3.45, 5.175], "pivot": [19.875, 8.43952, -27.47822], "rotation": [90, 0, 0], "uv": [576, 583]},
						{"origin": [18.375, 12.60404, -33.36774], "size": [6, 3.45, 5.175], "pivot": [19.875, 12.60404, -29.91774], "rotation": [135, 0, 0], "uv": [0, 584]}
					]
				},
				{
					"name": "wheelR",
					"parent": "T-90",
					"pivot": [0, 6, -3.25]
				},
				{
					"name": "wheel9",
					"parent": "wheelR",
					"pivot": [-22.25, 9.58952, -46.375],
					"cubes": [
						{"origin": [-23, 5.425, -48.1], "size": [2, 4.6, 3.45], "uv": [612, 559]},
						{"origin": [-23, 7.05134, -50.87634], "size": [2, 4.6, 3.45], "pivot": [-22, 7.05134, -49.72634], "rotation": [-45, 0, 0], "uv": [610, 612]},
						{"origin": [-23, 10.16452, -51.68952], "size": [2, 4.6, 3.45], "pivot": [-22, 10.16452, -50.53952], "rotation": [-90, 0, 0], "uv": [180, 613]},
						{"origin": [-23, 12.94086, -50.06318], "size": [2, 4.6, 3.45], "pivot": [-22, 12.94086, -48.91318], "rotation": [-135, 0, 0], "uv": [246, 613]},
						{"origin": [-23, 13.75404, -46.95], "size": [2, 4.6, 3.45], "pivot": [-22, 13.75404, -45.8], "rotation": [180, 0, 0], "uv": [400, 613]},
						{"origin": [-23, 12.12769, -44.17366], "size": [2, 4.6, 3.45], "pivot": [-22, 12.12769, -43.02366], "rotation": [135, 0, 0], "uv": [410, 613]},
						{"origin": [-23, 9.01452, -43.36048], "size": [2, 4.6, 3.45], "pivot": [-22, 9.01452, -42.21048], "rotation": [90, 0, 0], "uv": [476, 613]},
						{"origin": [-23, 6.23818, -44.98682], "size": [2, 4.6, 3.45], "pivot": [-22, 6.23818, -43.83682], "rotation": [45, 0, 0], "uv": [538, 613]},
						{"origin": [-25, 5.425, -48.1], "size": [4, 2.3, 3.45], "uv": [608, 383]},
						{"origin": [-25, 6.23818, -44.98682], "size": [4, 2.3, 3.45], "pivot": [-22, 6.23818, -43.83682], "rotation": [45, 0, 0], "uv": [608, 388]},
						{"origin": [-25, 9.01452, -43.36048], "size": [4, 2.3, 3.45], "pivot": [-22, 9.01452, -42.21048], "rotation": [90, 0, 0], "uv": [608, 393]},
						{"origin": [-25, 12.12769, -44.17366], "size": [4, 2.3, 3.45], "pivot": [-22, 12.12769, -43.02366], "rotation": [135, 0, 0], "uv": [608, 398]},
						{"origin": [-25, 13.75404, -46.95], "size": [4, 2.3, 3.45], "pivot": [-22, 13.75404, -45.8], "rotation": [180, 0, 0], "uv": [608, 403]},
						{"origin": [-25, 7.05134, -50.87634], "size": [4, 2.3, 3.45], "pivot": [-22, 7.05134, -49.72634], "rotation": [-45, 0, 0], "uv": [608, 452]},
						{"origin": [-25, 10.16452, -51.68952], "size": [4, 2.3, 3.45], "pivot": [-22, 10.16452, -50.53952], "rotation": [-90, 0, 0], "uv": [608, 457]},
						{"origin": [-25, 12.94086, -50.06318], "size": [4, 2.3, 3.45], "pivot": [-22, 12.94086, -48.91318], "rotation": [-135, 0, 0], "uv": [608, 462]}
					]
				},
				{
					"name": "wheel10",
					"parent": "wheelR",
					"pivot": [-22.25, 9.58952, 47.925],
					"cubes": [
						{"origin": [-23, 5.425, 46.2], "size": [2, 4.6, 3.45], "uv": [548, 613]},
						{"origin": [-23, 7.05134, 48.97634], "size": [2, 4.6, 3.45], "pivot": [-22, 7.05134, 51.27634], "rotation": [45, 0, 0], "uv": [558, 613]},
						{"origin": [-23, 10.16452, 49.78952], "size": [2, 4.6, 3.45], "pivot": [-22, 10.16452, 52.08952], "rotation": [90, 0, 0], "uv": [568, 613]},
						{"origin": [-23, 12.94086, 48.16318], "size": [2, 4.6, 3.45], "pivot": [-22, 12.94086, 50.46318], "rotation": [135, 0, 0], "uv": [578, 613]},
						{"origin": [-23, 13.75404, 45.05], "size": [2, 4.6, 3.45], "pivot": [-22, 13.75404, 47.35], "rotation": [-180, 0, 0], "uv": [0, 614]},
						{"origin": [-23, 12.12769, 42.27366], "size": [2, 4.6, 3.45], "pivot": [-22, 12.12769, 44.57366], "rotation": [-135, 0, 0], "uv": [108, 614]},
						{"origin": [-23, 9.01452, 41.46048], "size": [2, 4.6, 3.45], "pivot": [-22, 9.01452, 43.76048], "rotation": [-90, 0, 0], "uv": [118, 614]},
						{"origin": [-23, 6.23818, 43.08682], "size": [2, 4.6, 3.45], "pivot": [-22, 6.23818, 45.38682], "rotation": [-45, 0, 0], "uv": [128, 614]},
						{"origin": [-25, 5.425, 46.2], "size": [4, 2.3, 3.45], "uv": [608, 467]},
						{"origin": [-25, 6.23818, 43.08682], "size": [4, 2.3, 3.45], "pivot": [-22, 6.23818, 45.38682], "rotation": [-45, 0, 0], "uv": [608, 472]},
						{"origin": [-25, 9.01452, 41.46048], "size": [4, 2.3, 3.45], "pivot": [-22, 9.01452, 43.76048], "rotation": [-90, 0, 0], "uv": [608, 477]},
						{"origin": [-25, 12.12769, 42.27366], "size": [4, 2.3, 3.45], "pivot": [-22, 12.12769, 44.57366], "rotation": [-135, 0, 0], "uv": [608, 482]},
						{"origin": [-25, 13.75404, 45.05], "size": [4, 2.3, 3.45], "pivot": [-22, 13.75404, 47.35], "rotation": [-180, 0, 0], "uv": [608, 487]},
						{"origin": [-25, 7.05134, 48.97634], "size": [4, 2.3, 3.45], "pivot": [-22, 7.05134, 51.27634], "rotation": [45, 0, 0], "uv": [608, 520]},
						{"origin": [-25, 10.16452, 49.78952], "size": [4, 2.3, 3.45], "pivot": [-22, 10.16452, 52.08952], "rotation": [90, 0, 0], "uv": [608, 525]},
						{"origin": [-25, 12.94086, 48.16318], "size": [4, 2.3, 3.45], "pivot": [-22, 12.94086, 50.46318], "rotation": [135, 0, 0], "uv": [608, 530]}
					]
				},
				{
					"name": "wheel11",
					"parent": "wheelR",
					"pivot": [-20.25, 7.57702, 36.425],
					"cubes": [
						{"origin": [-21.375, 1.33024, 33.8375], "size": [3, 6.9, 5.175], "uv": [598, 583]},
						{"origin": [-21.375, 3.76976, 38.00202], "size": [3, 6.9, 5.175], "pivot": [-19.875, 3.76976, 41.45202], "rotation": [45, 0, 0], "uv": [598, 594]},
						{"origin": [-21.375, 8.43952, 39.22178], "size": [3, 6.9, 5.175], "pivot": [-19.875, 8.43952, 42.67178], "rotation": [90, 0, 0], "uv": [600, 52]},
						{"origin": [-21.375, 12.60404, 36.78226], "size": [3, 6.9, 5.175], "pivot": [-19.875, 12.60404, 40.23226], "rotation": [135, 0, 0], "uv": [600, 63]},
						{"origin": [-21.375, 13.8238, 32.1125], "size": [3, 6.9, 5.175], "pivot": [-19.875, 13.8238, 35.5625], "rotation": [-180, 0, 0], "uv": [600, 74]},
						{"origin": [-21.375, 11.38428, 27.94798], "size": [3, 6.9, 5.175], "pivot": [-19.875, 11.38428, 31.39798], "rotation": [-135, 0, 0], "uv": [600, 85]},
						{"origin": [-21.375, 6.71452, 26.72822], "size": [3, 6.9, 5.175], "pivot": [-19.875, 6.71452, 30.17822], "rotation": [-90, 0, 0], "uv": [530, 601]},
						{"origin": [-21.375, 2.55, 29.16774], "size": [3, 6.9, 5.175], "pivot": [-19.875, 2.55, 32.61774], "rotation": [-45, 0, 0], "uv": [602, 96]},
						{"origin": [-24.375, 1.33024, 33.8375], "size": [6, 3.45, 5.175], "uv": [584, 28]},
						{"origin": [-24.375, 2.55, 29.16774], "size": [6, 3.45, 5.175], "pivot": [-19.875, 2.55, 32.61774], "rotation": [-45, 0, 0], "uv": [584, 36]},
						{"origin": [-24.375, 6.71452, 26.72822], "size": [6, 3.45, 5.175], "pivot": [-19.875, 6.71452, 30.17822], "rotation": [-90, 0, 0], "uv": [584, 44]},
						{"origin": [-24.375, 11.38428, 27.94798], "size": [6, 3.45, 5.175], "pivot": [-19.875, 11.38428, 31.39798], "rotation": [-135, 0, 0], "uv": [584, 114]},
						{"origin": [-24.375, 13.8238, 32.1125], "size": [6, 3.45, 5.175], "pivot": [-19.875, 13.8238, 35.5625], "rotation": [-180, 0, 0], "uv": [584, 122]},
						{"origin": [-24.375, 3.76976, 38.00202], "size": [6, 3.45, 5.175], "pivot": [-19.875, 3.76976, 41.45202], "rotation": [45, 0, 0], "uv": [584, 130]},
						{"origin": [-24.375, 8.43952, 39.22178], "size": [6, 3.45, 5.175], "pivot": [-19.875, 8.43952, 42.67178], "rotation": [90, 0, 0], "uv": [584, 138]},
						{"origin": [-24.375, 12.60404, 36.78226], "size": [6, 3.45, 5.175], "pivot": [-19.875, 12.60404, 40.23226], "rotation": [135, 0, 0], "uv": [144, 584]}
					]
				},
				{
					"name": "wheel12",
					"parent": "wheelR",
					"pivot": [-20.25, 7.57702, 22.625],
					"cubes": [
						{"origin": [-21.375, 1.33024, 20.0375], "size": [3, 6.9, 5.175], "uv": [602, 146]},
						{"origin": [-21.375, 3.76976, 24.20202], "size": [3, 6.9, 5.175], "pivot": [-19.875, 3.76976, 27.65202], "rotation": [45, 0, 0], "uv": [602, 157]},
						{"origin": [-21.375, 8.43952, 25.42178], "size": [3, 6.9, 5.175], "pivot": [-19.875, 8.43952, 28.87178], "rotation": [90, 0, 0], "uv": [180, 602]},
						{"origin": [-21.375, 12.60404, 22.98226], "size": [3, 6.9, 5.175], "pivot": [-19.875, 12.60404, 26.43226], "rotation": [135, 0, 0], "uv": [246, 602]},
						{"origin": [-21.375, 13.8238, 18.3125], "size": [3, 6.9, 5.175], "pivot": [-19.875, 13.8238, 21.7625], "rotation": [-180, 0, 0], "uv": [404, 602]},
						{"origin": [-21.375, 11.38428, 14.14798], "size": [3, 6.9, 5.175], "pivot": [-19.875, 11.38428, 17.59798], "rotation": [-135, 0, 0], "uv": [476, 602]},
						{"origin": [-21.375, 6.71452, 12.92822], "size": [3, 6.9, 5.175], "pivot": [-19.875, 6.71452, 16.37822], "rotation": [-90, 0, 0], "uv": [546, 602]},
						{"origin": [-21.375, 2.55, 15.36774], "size": [3, 6.9, 5.175], "pivot": [-19.875, 2.55, 18.81774], "rotation": [-45, 0, 0], "uv": [562, 602]},
						{"origin": [-24.375, 1.33024, 20.0375], "size": [6, 3.45, 5.175], "uv": [330, 584]},
						{"origin": [-24.375, 2.55, 15.36774], "size": [6, 3.45, 5.175], "pivot": [-19.875, 2.55, 18.81774], "rotation": [-45, 0, 0], "uv": [352, 584]},
						{"origin": [-24.375, 6.71452, 12.92822], "size": [6, 3.45, 5.175], "pivot": [-19.875, 6.71452, 16.37822], "rotation": [-90, 0, 0], "uv": [280, 585]},
						{"origin": [-24.375, 11.38428, 14.14798], "size": [6, 3.45, 5.175], "pivot": [-19.875, 11.38428, 17.59798], "rotation": [-135, 0, 0], "uv": [586, 297]},
						{"origin": [-24.375, 13.8238, 18.3125], "size": [6, 3.45, 5.175], "pivot": [-19.875, 13.8238, 21.7625], "rotation": [-180, 0, 0], "uv": [586, 305]},
						{"origin": [-24.375, 3.76976, 24.20202], "size": [6, 3.45, 5.175], "pivot": [-19.875, 3.76976, 27.65202], "rotation": [45, 0, 0], "uv": [586, 313]},
						{"origin": [-24.375, 8.43952, 25.42178], "size": [6, 3.45, 5.175], "pivot": [-19.875, 8.43952, 28.87178], "rotation": [90, 0, 0], "uv": [586, 321]},
						{"origin": [-24.375, 12.60404, 22.98226], "size": [6, 3.45, 5.175], "pivot": [-19.875, 12.60404, 26.43226], "rotation": [135, 0, 0], "uv": [586, 329]}
					]
				},
				{
					"name": "wheel13",
					"parent": "wheelR",
					"pivot": [-20.25, 7.57702, 8.825],
					"cubes": [
						{"origin": [-21.375, 1.33024, 6.2375], "size": [3, 6.9, 5.175], "uv": [578, 602]},
						{"origin": [-21.375, 3.76976, 10.40202], "size": [3, 6.9, 5.175], "pivot": [-19.875, 3.76976, 13.85202], "rotation": [45, 0, 0], "uv": [0, 603]},
						{"origin": [-21.375, 8.43952, 11.62178], "size": [3, 6.9, 5.175], "pivot": [-19.875, 8.43952, 15.07178], "rotation": [90, 0, 0], "uv": [124, 603]},
						{"origin": [-21.375, 12.60404, 9.18226], "size": [3, 6.9, 5.175], "pivot": [-19.875, 12.60404, 12.63226], "rotation": [135, 0, 0], "uv": [140, 603]},
						{"origin": [-21.375, 13.8238, 4.5125], "size": [3, 6.9, 5.175], "pivot": [-19.875, 13.8238, 7.9625], "rotation": [-180, 0, 0], "uv": [314, 603]},
						{"origin": [-21.375, 11.38428, 0.34798], "size": [3, 6.9, 5.175], "pivot": [-19.875, 11.38428, 3.79798], "rotation": [-135, 0, 0], "uv": [330, 603]},
						{"origin": [-21.375, 6.71452, -0.87178], "size": [3, 6.9, 5.175], "pivot": [-19.875, 6.71452, 2.57822], "rotation": [-90, 0, 0], "uv": [346, 603]},
						{"origin": [-21.375, 2.55, 1.56774], "size": [3, 6.9, 5.175], "pivot": [-19.875, 2.55, 5.01774], "rotation": [-45, 0, 0], "uv": [604, 191]},
						{"origin": [-24.375, 1.33024, 6.2375], "size": [6, 3.45, 5.175], "uv": [586, 337]},
						{"origin": [-24.375, 2.55, 1.56774], "size": [6, 3.45, 5.175], "pivot": [-19.875, 2.55, 5.01774], "rotation": [-45, 0, 0], "uv": [586, 345]},
						{"origin": [-24.375, 6.71452, -0.87178], "size": [6, 3.45, 5.175], "pivot": [-19.875, 6.71452, 2.57822], "rotation": [-90, 0, 0], "uv": [586, 353]},
						{"origin": [-24.375, 11.38428, 0.34798], "size": [6, 3.45, 5.175], "pivot": [-19.875, 11.38428, 3.79798], "rotation": [-135, 0, 0], "uv": [586, 361]},
						{"origin": [-24.375, 13.8238, 4.5125], "size": [6, 3.45, 5.175], "pivot": [-19.875, 13.8238, 7.9625], "rotation": [-180, 0, 0], "uv": [586, 369]},
						{"origin": [-24.375, 3.76976, 10.40202], "size": [6, 3.45, 5.175], "pivot": [-19.875, 3.76976, 13.85202], "rotation": [45, 0, 0], "uv": [586, 377]},
						{"origin": [-24.375, 8.43952, 11.62178], "size": [6, 3.45, 5.175], "pivot": [-19.875, 8.43952, 15.07178], "rotation": [90, 0, 0], "uv": [586, 385]},
						{"origin": [-24.375, 12.60404, 9.18226], "size": [6, 3.45, 5.175], "pivot": [-19.875, 12.60404, 12.63226], "rotation": [135, 0, 0], "uv": [586, 393]}
					]
				},
				{
					"name": "wheel14",
					"parent": "wheelR",
					"pivot": [-20.25, 7.57702, -6.125],
					"cubes": [
						{"origin": [-21.375, 1.33024, -8.7125], "size": [3, 6.9, 5.175], "uv": [604, 202]},
						{"origin": [-21.375, 3.76976, -4.54798], "size": [3, 6.9, 5.175], "pivot": [-19.875, 3.76976, -1.09798], "rotation": [45, 0, 0], "uv": [604, 213]},
						{"origin": [-21.375, 8.43952, -3.32822], "size": [3, 6.9, 5.175], "pivot": [-19.875, 8.43952, 0.12178], "rotation": [90, 0, 0], "uv": [262, 604]},
						{"origin": [-21.375, 12.60404, -5.76774], "size": [3, 6.9, 5.175], "pivot": [-19.875, 12.60404, -2.31774], "rotation": [135, 0, 0], "uv": [278, 604]},
						{"origin": [-21.375, 13.8238, -10.4375], "size": [3, 6.9, 5.175], "pivot": [-19.875, 13.8238, -6.9875], "rotation": [-180, 0, 0], "uv": [594, 605]},
						{"origin": [-21.375, 11.38428, -14.60202], "size": [3, 6.9, 5.175], "pivot": [-19.875, 11.38428, -11.15202], "rotation": [-135, 0, 0], "uv": [606, 28]},
						{"origin": [-21.375, 6.71452, -15.82178], "size": [3, 6.9, 5.175], "pivot": [-19.875, 6.71452, -12.37178], "rotation": [-90, 0, 0], "uv": [606, 39]},
						{"origin": [-21.375, 2.55, -13.38226], "size": [3, 6.9, 5.175], "pivot": [-19.875, 2.55, -9.93226], "rotation": [-45, 0, 0], "uv": [606, 107]},
						{"origin": [-24.375, 1.33024, -8.7125], "size": [6, 3.45, 5.175], "uv": [586, 401]},
						{"origin": [-24.375, 2.55, -13.38226], "size": [6, 3.45, 5.175], "pivot": [-19.875, 2.55, -9.93226], "rotation": [-45, 0, 0], "uv": [586, 566]},
						{"origin": [-24.375, 6.71452, -15.82178], "size": [6, 3.45, 5.175], "pivot": [-19.875, 6.71452, -12.37178], "rotation": [-90, 0, 0], "uv": [206, 587]},
						{"origin": [-24.375, 11.38428, -14.60202], "size": [6, 3.45, 5.175], "pivot": [-19.875, 11.38428, -11.15202], "rotation": [-135, 0, 0], "uv": [374, 587]},
						{"origin": [-24.375, 13.8238, -10.4375], "size": [6, 3.45, 5.175], "pivot": [-19.875, 13.8238, -6.9875], "rotation": [-180, 0, 0], "uv": [588, 175]},
						{"origin": [-24.375, 3.76976, -4.54798], "size": [6, 3.45, 5.175], "pivot": [-19.875, 3.76976, -1.09798], "rotation": [45, 0, 0], "uv": [588, 183]},
						{"origin": [-24.375, 8.43952, -3.32822], "size": [6, 3.45, 5.175], "pivot": [-19.875, 8.43952, 0.12178], "rotation": [90, 0, 0], "uv": [588, 269]},
						{"origin": [-24.375, 12.60404, -5.76774], "size": [6, 3.45, 5.175], "pivot": [-19.875, 12.60404, -2.31774], "rotation": [135, 0, 0], "uv": [588, 277]}
					]
				},
				{
					"name": "wheel15",
					"parent": "wheelR",
					"pivot": [-20.25, 7.57702, -19.925],
					"cubes": [
						{"origin": [-21.375, 1.33024, -22.5125], "size": [3, 6.9, 5.175], "uv": [606, 118]},
						{"origin": [-21.375, 3.76976, -18.34798], "size": [3, 6.9, 5.175], "pivot": [-19.875, 3.76976, -14.89798], "rotation": [45, 0, 0], "uv": [606, 129]},
						{"origin": [-21.375, 8.43952, -17.12822], "size": [3, 6.9, 5.175], "pivot": [-19.875, 8.43952, -13.67822], "rotation": [90, 0, 0], "uv": [156, 606]},
						{"origin": [-21.375, 12.60404, -19.56774], "size": [3, 6.9, 5.175], "pivot": [-19.875, 12.60404, -16.11774], "rotation": [135, 0, 0], "uv": [196, 606]},
						{"origin": [-21.375, 13.8238, -24.2375], "size": [3, 6.9, 5.175], "pivot": [-19.875, 13.8238, -20.7875], "rotation": [-180, 0, 0], "uv": [362, 606]},
						{"origin": [-21.375, 11.38428, -28.40202], "size": [3, 6.9, 5.175], "pivot": [-19.875, 11.38428, -24.95202], "rotation": [-135, 0, 0], "uv": [294, 607]},
						{"origin": [-21.375, 6.71452, -29.62178], "size": [3, 6.9, 5.175], "pivot": [-19.875, 6.71452, -26.17178], "rotation": [-90, 0, 0], "uv": [608, 0]},
						{"origin": [-21.375, 2.55, -27.18226], "size": [3, 6.9, 5.175], "pivot": [-19.875, 2.55, -23.73226], "rotation": [-45, 0, 0], "uv": [608, 11]},
						{"origin": [-24.375, 1.33024, -22.5125], "size": [6, 3.45, 5.175], "uv": [588, 285]},
						{"origin": [-24.375, 2.55, -27.18226], "size": [6, 3.45, 5.175], "pivot": [-19.875, 2.55, -23.73226], "rotation": [-45, 0, 0], "uv": [302, 588]},
						{"origin": [-24.375, 6.71452, -29.62178], "size": [6, 3.45, 5.175], "pivot": [-19.875, 6.71452, -26.17178], "rotation": [-90, 0, 0], "uv": [44, 589]},
						{"origin": [-24.375, 11.38428, -28.40202], "size": [6, 3.45, 5.175], "pivot": [-19.875, 11.38428, -24.95202], "rotation": [-135, 0, 0], "uv": [66, 589]},
						{"origin": [-24.375, 13.8238, -24.2375], "size": [6, 3.45, 5.175], "pivot": [-19.875, 13.8238, -20.7875], "rotation": [-180, 0, 0], "uv": [88, 589]},
						{"origin": [-24.375, 3.76976, -18.34798], "size": [6, 3.45, 5.175], "pivot": [-19.875, 3.76976, -14.89798], "rotation": [45, 0, 0], "uv": [22, 590]},
						{"origin": [-24.375, 8.43952, -17.12822], "size": [6, 3.45, 5.175], "pivot": [-19.875, 8.43952, -13.67822], "rotation": [90, 0, 0], "uv": [110, 590]},
						{"origin": [-24.375, 12.60404, -19.56774], "size": [6, 3.45, 5.175], "pivot": [-19.875, 12.60404, -16.11774], "rotation": [135, 0, 0], "uv": [228, 590]}
					]
				},
				{
					"name": "wheel16",
					"parent": "wheelR",
					"pivot": [-20.25, 7.57702, -33.725],
					"cubes": [
						{"origin": [-21.375, 1.33024, -36.3125], "size": [3, 6.9, 5.175], "uv": [32, 608]},
						{"origin": [-21.375, 3.76976, -32.14798], "size": [3, 6.9, 5.175], "pivot": [-19.875, 3.76976, -28.69798], "rotation": [45, 0, 0], "uv": [48, 608]},
						{"origin": [-21.375, 8.43952, -30.92822], "size": [3, 6.9, 5.175], "pivot": [-19.875, 8.43952, -27.47822], "rotation": [90, 0, 0], "uv": [64, 608]},
						{"origin": [-21.375, 12.60404, -33.36774], "size": [3, 6.9, 5.175], "pivot": [-19.875, 12.60404, -29.91774], "rotation": [135, 0, 0], "uv": [80, 608]},
						{"origin": [-21.375, 13.8238, -38.0375], "size": [3, 6.9, 5.175], "pivot": [-19.875, 13.8238, -34.5875], "rotation": [-180, 0, 0], "uv": [608, 255]},
						{"origin": [-21.375, 11.38428, -42.20202], "size": [3, 6.9, 5.175], "pivot": [-19.875, 11.38428, -38.75202], "rotation": [-135, 0, 0], "uv": [608, 293]},
						{"origin": [-21.375, 6.71452, -43.42178], "size": [3, 6.9, 5.175], "pivot": [-19.875, 6.71452, -39.97178], "rotation": [-90, 0, 0], "uv": [608, 304]},
						{"origin": [-21.375, 2.55, -40.98226], "size": [3, 6.9, 5.175], "pivot": [-19.875, 2.55, -37.53226], "rotation": [-45, 0, 0], "uv": [608, 315]},
						{"origin": [-24.375, 1.33024, -36.3125], "size": [6, 3.45, 5.175], "uv": [590, 247]},
						{"origin": [-24.375, 2.55, -40.98226], "size": [6, 3.45, 5.175], "pivot": [-19.875, 2.55, -37.53226], "rotation": [-45, 0, 0], "uv": [590, 409]},
						{"origin": [-24.375, 6.71452, -43.42178], "size": [6, 3.45, 5.175], "pivot": [-19.875, 6.71452, -39.97178], "rotation": [-90, 0, 0], "uv": [590, 417]},
						{"origin": [-24.375, 11.38428, -42.20202], "size": [6, 3.45, 5.175], "pivot": [-19.875, 11.38428, -38.75202], "rotation": [-135, 0, 0], "uv": [590, 425]},
						{"origin": [-24.375, 13.8238, -38.0375], "size": [6, 3.45, 5.175], "pivot": [-19.875, 13.8238, -34.5875], "rotation": [-180, 0, 0], "uv": [590, 433]},
						{"origin": [-24.375, 3.76976, -32.14798], "size": [6, 3.45, 5.175], "pivot": [-19.875, 3.76976, -28.69798], "rotation": [45, 0, 0], "uv": [438, 590]},
						{"origin": [-24.375, 8.43952, -30.92822], "size": [6, 3.45, 5.175], "pivot": [-19.875, 8.43952, -27.47822], "rotation": [90, 0, 0], "uv": [460, 590]},
						{"origin": [-24.375, 12.60404, -33.36774], "size": [6, 3.45, 5.175], "pivot": [-19.875, 12.60404, -29.91774], "rotation": [135, 0, 0], "uv": [512, 590]}
					]
				},
				{
					"name": "caterpillarL",
					"parent": "T-90",
					"pivot": [0, 6, -3.25],
					"cubes": [
						{"origin": [17.5, 14.05, -50.4], "size": [8, 1.15, 101.2], "uv": [0, 0]},
						{"origin": [17.5, -0.02904, -39.81532], "size": [8, 1.15, 81.075], "uv": [370, 297]},
						{"origin": [17.5, 9.88549, -54.90135], "size": [8, 1.15, 8.05], "pivot": [21.5, 10.46049, -52.02635], "rotation": [65, 0, 0], "uv": [108, 564]},
						{"origin": [17.5, 6.50643, -64.10036], "size": [8, 1.15, 16.1], "pivot": [21.5, 7.08143, -50.87536], "rotation": [150, 0, 0], "uv": [114, 487]},
						{"origin": [17.5, 9.88549, 48.40135], "size": [8, 1.15, 8.05], "pivot": [21.5, 10.46049, 53.57635], "rotation": [-57.5, 0, 0], "uv": [242, 565]},
						{"origin": [17.5, 6.50643, 49.55036], "size": [8, 1.15, 16.1], "pivot": [21.5, 7.08143, 52.42536], "rotation": [-150, 0, 0], "uv": [534, 197]}
					]
				},
				{
					"name": "caterpillarR",
					"parent": "T-90",
					"pivot": [0, 6, -3.25],
					"cubes": [
						{"origin": [-25.5, 14.05, -49.25], "size": [8, 1.15, 101.2], "uv": [0, 102]},
						{"origin": [-25.5, -0.02904, -39.81532], "size": [8, 1.15, 81.075], "uv": [370, 379]},
						{"origin": [-25.5, 9.88549, -54.90135], "size": [8, 1.15, 8.05], "pivot": [-21.5, 10.46049, -52.02635], "rotation": [57.5, 0, 0], "uv": [478, 565]},
						{"origin": [-25.5, 6.50643, -64.10036], "size": [8, 1.15, 16.1], "pivot": [-21.5, 7.08143, -50.87536], "rotation": [150, 0, 0], "uv": [534, 214]},
						{"origin": [-25.5, 9.88549, 48.40135], "size": [8, 1.15, 8.05], "pivot": [-21.5, 10.46049, 53.57635], "rotation": [-65, 0, 0], "uv": [0, 567]},
						{"origin": [-25.5, 6.50643, 49.55036], "size": [8, 1.15, 16.1], "pivot": [-21.5, 7.08143, 52.42536], "rotation": [-150, 0, 0], "uv": [492, 535]}
					]
				}
			]
		}
	]
}